corpusparser/__init__.py
corpusparser/corpus.py
corpusparser/corpus_element.py
corpusparser/document.py
corpusparser/sentence.py
corpusparser/word.py
corpusparser-0.0.2.dist-info/METADATA
corpusparser-0.0.2.dist-info/WHEEL
corpusparser-0.0.2.dist-info/licenses/LICENSE
corpusparser-0.0.2.dist-info/RECORD
