Metadata-Version: 2.1
Name: corpusparser
Version: 0.0.2
Summary: Python library for importing and using corpus data in linguistic research
Project-URL: Homepage, https://github.com/idpattison/corpusparser
Project-URL: Issues, https://github.com/idpattison/corpusparser/issues
Author-email: Ian Pattison <ianpattison2@gmail.com>
License-File: LICENSE
Classifier: License :: OSI Approved :: MIT License
Classifier: Operating System :: OS Independent
Classifier: Programming Language :: Python :: 3
Requires-Python: >=3.7
Requires-Dist: benepar
Requires-Dist: spacy
